mess_client/__init__.py
mess_client/client.py
mess_client/client/__init__.py
mess_client/client/add_contact.py
mess_client/client/database.py
mess_client/client/del_contact.py
mess_client/client/main_window.py
mess_client/client/main_window_conv.py
mess_client/client/start_dialog.py
mess_client/client/transport.py
mess_client/common/__init__.py
mess_client/common/decos.py
mess_client/common/descryptors.py
mess_client/common/errors.py
mess_client/common/metaclasses.py
mess_client/common/utils.py
mess_client/common/variables.py
mess_client/logs/__init__.py
mess_client/logs/config_client_log.py
mess_client/logs/config_server_log.py
mess_client/unit_tests/__init__.py
mess_client/unit_tests/test_client.py
mess_client/unit_tests/test_utils.py
vitalijtverskoj_mess_client-0.2.dist-info/LICENSE.txt
vitalijtverskoj_mess_client-0.2.dist-info/METADATA
vitalijtverskoj_mess_client-0.2.dist-info/WHEEL
vitalijtverskoj_mess_client-0.2.dist-info/top_level.txt
vitalijtverskoj_mess_client-0.2.dist-info/RECORD
