Metadata-Version: 2.1
Name: vitalijtverskoj-mess-client
Version: 0.2
Summary: Client packet
Author: Geek Brains
Author-email: gb@gb.ru
License-File: LICENSE.txt
